{"nodes": [{"id": "frontend_src_assets_fonts_ofl_txt_document", "label": "OFL.txt font license", "file_type": "document", "source_file": "frontend/src/assets/fonts/OFL.txt", "source_location": null, "source_url": null, "captured_at": null, "author": null, "contributor": null}, {"id": "sil_ofl_1_1_license_concept", "label": "SIL Open Font License 1.1", "file_type": "license", "source_file": "frontend/src/assets/fonts/OFL.txt", "source_location": null, "source_url": null, "captured_at": null, "author": null, "contributor": null}], "edges": [{"source": "kube_lens_project", "target": "sil_ofl_1_1_license_concept", "relation": "conceptually_related_to", "confidence": "INFERRED", "confidence_score": 0.7, "source_file": "frontend/src/assets/fonts/OFL.txt", "source_location": null, "weight": 1.0}], "hyperedges": []}